kol/__init__.py
kol/py.typed
kol/requirements-dev.txt
kol/requirements.txt
kol/formats/__init__.py
kol/formats/common.py
kol/formats/mjcf.py
kol/formats/urdf.py
kol/onshape/__init__.py
kol/onshape/api.py
kol/onshape/cached_api.py
kol/onshape/cacher.py
kol/onshape/client.py
kol/onshape/config.py
kol/onshape/download.py
kol/onshape/postprocess.py
kol/onshape/schema/__init__.py
kol/onshape/schema/assembly.py
kol/onshape/schema/common.py
kol/onshape/schema/document.py
kol/onshape/schema/elements.py
kol/onshape/schema/features.py
kol/onshape/schema/part.py
kol/passes/__init__.py
kol/passes/add_base_linkage.py
kol/passes/add_joint_separation.py
kol/passes/add_mjcf.py
kol/passes/convert_floats_to_consistent_types.py
kol/passes/exclude_collision_meshes.py
kol/passes/fix_inertias.py
kol/passes/flip_joints.py
kol/passes/make_convex_collision_mesh.py
kol/passes/merge_fixed_joints.py
kol/passes/move_collision_meshes.py
kol/passes/remove_extra_meshes.py
kol/passes/remove_internal_geometries.py
kol/passes/rotate_joints.py
kol/passes/separate_collision_meshes.py
kol/passes/shrink_collision_meshes.py
kol/passes/simplify_meshes.py
kol/passes/sort_sections.py
kol/passes/update_names.py
kol/passes/use_collision_meshes_as_visual_meshes.py
kol/passes/utils.py
kol/scripts/__init__.py
kol/scripts/cli.py
kol/scripts/mujoco.py
kol/scripts/pybullet.py
kol/scripts/bullet/plane.obj
kol/scripts/bullet/plane.urdf
kol/utils/__init__.py
kol/utils/errors.py
kol/utils/geometry.py
kol/utils/logging.py
kol/utils/mesh.py
kol/utils/resolvers.py
kol/utils/update_joints.py
kscale_onshape_library-0.2.21.dist-info/licenses/LICENSE
kscale_onshape_library-0.2.21.dist-info/METADATA
kscale_onshape_library-0.2.21.dist-info/WHEEL
kscale_onshape_library-0.2.21.dist-info/entry_points.txt
kscale_onshape_library-0.2.21.dist-info/top_level.txt
kscale_onshape_library-0.2.21.dist-info/RECORD
