Metadata-Version: 2.4
Name: kscale-onshape-library
Version: 0.2.21
Summary: K-Scale's library for programmatically interacting with OnShape
Home-page: https://github.com/kscalelabs/onshape
Author: Benjamin Bolte
Requires-Python: >=3.11
License-File: LICENSE
Requires-Dist: asyncstdlib
Requires-Dist: httpx
Requires-Dist: networkx
Requires-Dist: numpy
Requires-Dist: numpy-stl
Requires-Dist: omegaconf
Requires-Dist: pydantic
Requires-Dist: scipy
Requires-Dist: trimesh
Provides-Extra: dev
Requires-Dist: black; extra == "dev"
Requires-Dist: darglint; extra == "dev"
Requires-Dist: isort; extra == "dev"
Requires-Dist: mypy; extra == "dev"
Requires-Dist: pytest; extra == "dev"
Requires-Dist: ruff; extra == "dev"
Requires-Dist: isort; extra == "dev"
Provides-Extra: mujoco
Requires-Dist: mujoco; extra == "mujoco"
Requires-Dist: urdf2mjcf; extra == "mujoco"
Requires-Dist: mujoco-python-viewer; extra == "mujoco"
Provides-Extra: open3d
Requires-Dist: open3d; extra == "open3d"
Provides-Extra: all
Requires-Dist: black; extra == "all"
Requires-Dist: darglint; extra == "all"
Requires-Dist: isort; extra == "all"
Requires-Dist: mypy; extra == "all"
Requires-Dist: pytest; extra == "all"
Requires-Dist: ruff; extra == "all"
Requires-Dist: isort; extra == "all"
Requires-Dist: mujoco; extra == "all"
Requires-Dist: urdf2mjcf; extra == "all"
Requires-Dist: mujoco-python-viewer; extra == "all"
Requires-Dist: open3d; extra == "all"
Dynamic: author
Dynamic: description
Dynamic: description-content-type
Dynamic: home-page
Dynamic: license-file
Dynamic: provides-extra
Dynamic: requires-dist
Dynamic: requires-python
Dynamic: summary
